ping_stat/__about__.py
ping_stat/__constants__.py
ping_stat/__init__.py
ping_stat/config/__init__.py
ping_stat/config/arguments.py
ping_stat/errors/__init__.py
ping_stat/errors/utils.py
ping_stat/logging/__init__.py
ping_stat/main.py
ping_stat/models/__init__.py
ping_stat/models/gui/__init__.py
ping_stat/models/gui/windows/__init__.py
ping_stat/models/gui/windows/errors.py
ping_stat/utils/__init__.py
ping_stat/utils/decorators.py
ping_stat/utils/helpers.py
ping_stat/utils/network.py
ping_stat/utils/workers/__init__.py
ping_stat/utils/workers/gui.py
ping_stat-1.0.dist-info/entry_points.txt
ping_stat-1.0.dist-info/METADATA
ping_stat-1.0.dist-info/WHEEL
ping_stat-1.0.dist-info/RECORD
